exosip2ctypes/__init__.py
exosip2ctypes/call.py
exosip2ctypes/context.py
exosip2ctypes/error.py
exosip2ctypes/event.py
exosip2ctypes/message.py
exosip2ctypes/register.py
exosip2ctypes/sdp.py
exosip2ctypes/utils.py
exosip2ctypes/version.py
exosip2ctypes/_c/__init__.py
exosip2ctypes/_c/authentication.py
exosip2ctypes/_c/call.py
exosip2ctypes/_c/conf.py
exosip2ctypes/_c/event.py
exosip2ctypes/_c/globs.py
exosip2ctypes/_c/lib.py
exosip2ctypes/_c/message.py
exosip2ctypes/_c/osip_body.py
exosip2ctypes/_c/osip_call_id.py
exosip2ctypes/_c/osip_content_length.py
exosip2ctypes/_c/osip_content_type.py
exosip2ctypes/_c/osip_error.py
exosip2ctypes/_c/osip_from.py
exosip2ctypes/_c/osip_header.py
exosip2ctypes/_c/osip_parser.py
exosip2ctypes/_c/register.py
exosip2ctypes/_c/sdp.py
exosip2ctypes/_c/utils.py
exosip2ctypes/tests/__init__.py
exosip2ctypes/tests/test_call.py
exosip2ctypes/tests/test_context.py
exosip2ctypes-1.2.4.dist-info/METADATA
exosip2ctypes-1.2.4.dist-info/RECORD
exosip2ctypes-1.2.4.dist-info/WHEEL
exosip2ctypes-1.2.4.dist-info/top_level.txt
