Metadata-Version: 2.1
Name: exosip2ctypes
Version: 1.2.4
Summary: libeXosip2 Python wrapper
Home-page: http://github.com/tanbro/exosip2ctypes
Author: Liu Xue Yan
Author-email: realtanbro@gmail.com
License: GPL
Keywords: sip osip osip2 libosip lilbosip2 eXosip eXosip2 libeXosip2 exosip2ctypes
Platform: UNKNOWN
Classifier: Development Status :: 5 - Production/Stable
Classifier: Intended Audience :: Developers
Classifier: Topic :: Communications :: Telephony
Classifier: License :: OSI Approved :: GNU General Public License (GPL)
Classifier: Programming Language :: Python
Classifier: Programming Language :: Python :: 2
Classifier: Programming Language :: Python :: 2.7
Classifier: Programming Language :: Python :: 3
Classifier: Programming Language :: Python :: 3.4
Classifier: Programming Language :: Python :: 3.5
Classifier: Programming Language :: Python :: 3.6
Classifier: Programming Language :: Python :: 3.7
Classifier: Programming Language :: Python :: Implementation :: CPython
Classifier: Programming Language :: Python :: Implementation :: PyPy
Requires-Python: >=2.7,!=3.0.*,!=3.1.*,!=3.2.*,!=3.3.*
Requires-Dist: futures; python_version < "3.0"
Requires-Dist: enum34; python_version < "3.4"
